datapizza/embedders/mistral/__init__.py
datapizza/embedders/mistral/mistral.py
datapizza_ai_embedders_mistral-0.0.1.dist-info/METADATA
datapizza_ai_embedders_mistral-0.0.1.dist-info/WHEEL
datapizza_ai_embedders_mistral-0.0.1.dist-info/RECORD
