Metadata-Version: 2.4
Name: datapizza-ai-embedders-mistral
Version: 0.0.1
Summary: Mistral embedder for the datapizza-ai framework
Author-email: Ivan Buttinoni <ivan.buttinoni@cibi.it>
License: MIT
Classifier: License :: OSI Approved :: MIT License
Classifier: Operating System :: OS Independent
Classifier: Programming Language :: Python :: 3
Requires-Python: <4,>=3.10.0
Requires-Dist: datapizza-ai-core<0.1.0,>=0.0.10
Requires-Dist: mistralai<2.0.0,>=1.2.0
